strcompat.py
strcompat-0.1.1.dist-info/licenses/LICENSE
strcompat-0.1.1.dist-info/METADATA
strcompat-0.1.1.dist-info/WHEEL
strcompat-0.1.1.dist-info/top_level.txt
strcompat-0.1.1.dist-info/RECORD
