Metadata-Version: 2.4
Name: strcompat
Version: 0.1.1
Summary: A Python library handling conversions `unicode` <-> UTF-8 `str`s (Python 2), `unicode` <-> URI `str`s (Python 2 and 3), and `unicode` <-> `str`s in the filesystem encoding (Python 2).
Author-email: Jifeng Wu <jifengwu2k@gmail.com>
License-Expression: MIT
Project-URL: Homepage, https://github.com/jifengwu2k/strcompat
Project-URL: Bug Tracker, https://github.com/jifengwu2k/strcompat/issues
Classifier: Programming Language :: Python :: 2
Classifier: Programming Language :: Python :: 3
Classifier: Operating System :: OS Independent
Requires-Python: >=2
License-File: LICENSE
Dynamic: license-file
